{
  "startTime": "2025-04-16T07:19:21.371Z",
  "endTime": "2025-04-16T07:19:24.448Z",
  "userAgents": [
    "Chrome 135.0.0.0 / Windows 11"
  ],
  "passed": 1,
  "total": 1,
  "skipped": 0,
  "fixtures": [
    {
      "name": "Comment area",
      "path": "C:\\Users\\Johan\\Desktop\\testcafe-demo\\tests\\commentArea.js",
      "meta": {},
      "tests": [
        {
          "name": "Should activate comment area when I have tried TestCafe is checked",
          "meta": {},
          "errs": [],
          "durationMs": 2014,
          "unstable": false,
          "screenshotPath": null,
          "skipped": false
        }
      ]
    }
  ],
  "warnings": []
}